shankskit/__init__.py
shankskit/shankskit.py
shankskit-0.1.2.dist-info/LICENSE
shankskit-0.1.2.dist-info/METADATA
shankskit-0.1.2.dist-info/WHEEL
shankskit-0.1.2.dist-info/top_level.txt
shankskit-0.1.2.dist-info/RECORD
