Metadata-Version: 2.1
Name: shankskit
Version: 0.1.2
Summary: A brief description of your library
Home-page: https://github.com/ShashankRaoCoding/shankskit
Author: Shashank Rao
Author-email: your.email@example.com
License: LGPL-3.0-or-later
Classifier: Programming Language :: Python :: 3
Classifier: License :: OSI Approved :: GNU Lesser General Public License v3 (LGPLv3)
Classifier: Operating System :: OS Independent
Requires-Python: >=3.6
License-File: LICENSE
